Netzwerk/__init__.py
Netzwerk/perceptron.py
Netzwerk_pkg_palasanimahesh46-0.0.5.dist-info/LICENSE
Netzwerk_pkg_palasanimahesh46-0.0.5.dist-info/METADATA
Netzwerk_pkg_palasanimahesh46-0.0.5.dist-info/WHEEL
Netzwerk_pkg_palasanimahesh46-0.0.5.dist-info/top_level.txt
Netzwerk_pkg_palasanimahesh46-0.0.5.dist-info/RECORD
